MANIFEST.in
README.txt
plonetheme.criticas-configure.zcml
setup.py
docs/AUTHORS.txt
docs/HISTORY.txt
docs/INSTALL.txt
docs/LICENSE.GPL
docs/LICENSE.txt
plonetheme/__init__.py
plonetheme.criticas.egg-info/PKG-INFO
plonetheme.criticas.egg-info/SOURCES.txt
plonetheme.criticas.egg-info/dependency_links.txt
plonetheme.criticas.egg-info/entry_points.txt
plonetheme.criticas.egg-info/namespace_packages.txt
plonetheme.criticas.egg-info/not-zip-safe
plonetheme.criticas.egg-info/requires.txt
plonetheme.criticas.egg-info/top_level.txt
plonetheme/criticas/__init__.py
plonetheme/criticas/configure.zcml
plonetheme/criticas/profiles.zcml
plonetheme/criticas/setuphandlers.py
plonetheme/criticas/skins.zcml
plonetheme/criticas/tests.py
plonetheme/criticas/version.txt
plonetheme/criticas/browser/__init__.py
plonetheme/criticas/browser/configure.zcml
plonetheme/criticas/browser/interfaces.py
plonetheme/criticas/browser/viewlet.pt
plonetheme/criticas/browser/viewlets.py
plonetheme/criticas/browser/images/README.txt
plonetheme/criticas/browser/images/cancel.jpg
plonetheme/criticas/browser/images/columnasinbordersearch.jpg
plonetheme/criticas/browser/images/lupasearch.jpg
plonetheme/criticas/browser/images/lupasearchcuadrada.jpg
plonetheme/criticas/browser/images/mas.jpg
plonetheme/criticas/browser/images/menos.jpg
plonetheme/criticas/browser/images/puntaredonda.png
plonetheme/criticas/browser/images/save.jpg
plonetheme/criticas/browser/stylesheets/README.txt
plonetheme/criticas/browser/stylesheets/main.css
plonetheme/criticas/browser/templates/colophon.pt
plonetheme/criticas/profiles/default/actions.xml
plonetheme/criticas/profiles/default/cssregistry.xml
plonetheme/criticas/profiles/default/import_steps.xml
plonetheme/criticas/profiles/default/jsregistry.xml
plonetheme/criticas/profiles/default/metadata.xml
plonetheme/criticas/profiles/default/plonetheme.criticas_various.txt
plonetheme/criticas/profiles/default/skins.xml
plonetheme/criticas/profiles/default/viewlets.xml
plonetheme/criticas/skins/plonetheme_criticas_custom_images/CONTENT.txt
plonetheme/criticas/skins/plonetheme_criticas_custom_images/mclogo.jpg
plonetheme/criticas/skins/plonetheme_criticas_custom_templates/CONTENT.txt
plonetheme/criticas/skins/plonetheme_criticas_styles/CONTENT.txt
plonetheme/criticas/skins/plonetheme_criticas_styles/IEFixes.css
