Metadata-Version: 1.0
Name: plonetheme.criticas
Version: 1.0.0
Summary: An installable theme for Plone 3.0
Home-page: http://svn.plone.org/svn/collective/plonetheme.criticas
Author: Marcelo Huens
Author-email: shuens@menttes.com
License: GPL
Keywords: web zope plone theme
Platform: UNKNOWN
Classifier: Framework :: Plone
Classifier: Programming Language :: Python
Classifier: Topic :: Software Development :: Libraries :: Python Modules
